{
  "annotations": {
    "list": [
      {
        "builtIn": 1,
        "datasource": {
          "type": "grafana",
          "uid": "-- Grafana --"
        },
        "enable": true,
        "hide": true,
        "iconColor": "rgba(0, 211, 255, 1)",
        "name": "Annotations & Alerts",
        "type": "dashboard"
      }
    ]
  },
  "editable": true,
  "fiscalYearStartMonth": 0,
  "graphTooltip": 0,
  "id": null,
  "links": [],
  "liveNow": false,
  "panels": [
    {
      "gridPos": {
        "h": 4,
        "w": 24,
        "x": 0,
        "y": 0
      },
      "id": 1,
      "options": {
        "content": "# 💾 NovaSight Backup Dashboard\n\nMonitoring backup status, storage usage, and recovery readiness.",
        "mode": "markdown"
      },
      "title": "",
      "transparent": true,
      "type": "text"
    },
    {
      "datasource": {
        "type": "prometheus",
        "uid": "${datasource}"
      },
      "fieldConfig": {
        "defaults": {
          "color": {
            "mode": "thresholds"
          },
          "mappings": [],
          "thresholds": {
            "mode": "absolute",
            "steps": [
              {
                "color": "green",
                "value": null
              },
              {
                "color": "yellow",
                "value": 21600
              },
              {
                "color": "red",
                "value": 28800
              }
            ]
          },
          "unit": "s"
        }
      },
      "gridPos": {
        "h": 6,
        "w": 6,
        "x": 0,
        "y": 4
      },
      "id": 2,
      "options": {
        "colorMode": "value",
        "graphMode": "none",
        "justifyMode": "center",
        "orientation": "auto",
        "reduceOptions": {
          "calcs": ["lastNotNull"],
          "fields": "",
          "values": false
        },
        "textMode": "auto"
      },
      "pluginVersion": "10.0.0",
      "targets": [
        {
          "expr": "novasight:backup:age_seconds:postgresql",
          "legendFormat": "PostgreSQL",
          "refId": "A"
        }
      ],
      "title": "PostgreSQL Backup Age",
      "type": "stat"
    },
    {
      "datasource": {
        "type": "prometheus",
        "uid": "${datasource}"
      },
      "fieldConfig": {
        "defaults": {
          "color": {
            "mode": "thresholds"
          },
          "mappings": [],
          "thresholds": {
            "mode": "absolute",
            "steps": [
              {
                "color": "green",
                "value": null
              },
              {
                "color": "yellow",
                "value": 86400
              },
              {
                "color": "red",
                "value": 172800
              }
            ]
          },
          "unit": "s"
        }
      },
      "gridPos": {
        "h": 6,
        "w": 6,
        "x": 6,
        "y": 4
      },
      "id": 3,
      "options": {
        "colorMode": "value",
        "graphMode": "none",
        "justifyMode": "center",
        "orientation": "auto",
        "reduceOptions": {
          "calcs": ["lastNotNull"],
          "fields": "",
          "values": false
        },
        "textMode": "auto"
      },
      "targets": [
        {
          "expr": "novasight:backup:age_seconds:clickhouse",
          "legendFormat": "ClickHouse",
          "refId": "A"
        }
      ],
      "title": "ClickHouse Backup Age",
      "type": "stat"
    },
    {
      "datasource": {
        "type": "prometheus",
        "uid": "${datasource}"
      },
      "fieldConfig": {
        "defaults": {
          "color": {
            "mode": "thresholds"
          },
          "mappings": [],
          "thresholds": {
            "mode": "absolute",
            "steps": [
              {
                "color": "green",
                "value": null
              },
              {
                "color": "yellow",
                "value": 3600
              },
              {
                "color": "red",
                "value": 7200
              }
            ]
          },
          "unit": "s"
        }
      },
      "gridPos": {
        "h": 6,
        "w": 6,
        "x": 12,
        "y": 4
      },
      "id": 4,
      "options": {
        "colorMode": "value",
        "graphMode": "none",
        "justifyMode": "center",
        "orientation": "auto",
        "reduceOptions": {
          "calcs": ["lastNotNull"],
          "fields": "",
          "values": false
        },
        "textMode": "auto"
      },
      "targets": [
        {
          "expr": "novasight:backup:age_seconds:redis",
          "legendFormat": "Redis",
          "refId": "A"
        }
      ],
      "title": "Redis Backup Age",
      "type": "stat"
    },
    {
      "datasource": {
        "type": "prometheus",
        "uid": "${datasource}"
      },
      "fieldConfig": {
        "defaults": {
          "color": {
            "mode": "thresholds"
          },
          "mappings": [],
          "thresholds": {
            "mode": "absolute",
            "steps": [
              {
                "color": "green",
                "value": null
              },
              {
                "color": "yellow",
                "value": 536870912000
              },
              {
                "color": "red",
                "value": 1099511627776
              }
            ]
          },
          "unit": "bytes"
        }
      },
      "gridPos": {
        "h": 6,
        "w": 6,
        "x": 18,
        "y": 4
      },
      "id": 5,
      "options": {
        "colorMode": "value",
        "graphMode": "none",
        "justifyMode": "center",
        "orientation": "auto",
        "reduceOptions": {
          "calcs": ["lastNotNull"],
          "fields": "",
          "values": false
        },
        "textMode": "auto"
      },
      "targets": [
        {
          "expr": "aws_s3_bucket_size_bytes{bucket=\"novasight-backups\"}",
          "legendFormat": "Total",
          "refId": "A"
        }
      ],
      "title": "Total Backup Storage",
      "type": "stat"
    },
    {
      "datasource": {
        "type": "prometheus",
        "uid": "${datasource}"
      },
      "fieldConfig": {
        "defaults": {
          "color": {
            "mode": "palette-classic"
          },
          "custom": {
            "axisCenteredZero": false,
            "axisColorMode": "text",
            "axisLabel": "",
            "axisPlacement": "auto",
            "barAlignment": 0,
            "drawStyle": "line",
            "fillOpacity": 10,
            "gradientMode": "none",
            "hideFrom": {
              "legend": false,
              "tooltip": false,
              "viz": false
            },
            "lineInterpolation": "linear",
            "lineWidth": 1,
            "pointSize": 5,
            "scaleDistribution": {
              "type": "linear"
            },
            "showPoints": "never",
            "spanNulls": false,
            "stacking": {
              "group": "A",
              "mode": "none"
            },
            "thresholdsStyle": {
              "mode": "off"
            }
          },
          "mappings": [],
          "thresholds": {
            "mode": "absolute",
            "steps": [
              {
                "color": "green",
                "value": null
              }
            ]
          },
          "unit": "short"
        }
      },
      "gridPos": {
        "h": 8,
        "w": 12,
        "x": 0,
        "y": 10
      },
      "id": 6,
      "options": {
        "legend": {
          "calcs": [],
          "displayMode": "list",
          "placement": "bottom",
          "showLegend": true
        },
        "tooltip": {
          "mode": "multi",
          "sort": "desc"
        }
      },
      "targets": [
        {
          "expr": "sum(kube_job_status_succeeded{job_name=~\"postgresql-backup.*\", namespace=\"novasight\"}) by (job_name)",
          "legendFormat": "PostgreSQL",
          "refId": "A"
        },
        {
          "expr": "sum(kube_job_status_succeeded{job_name=~\"clickhouse-backup.*\", namespace=\"novasight\"}) by (job_name)",
          "legendFormat": "ClickHouse",
          "refId": "B"
        },
        {
          "expr": "sum(kube_job_status_succeeded{job_name=~\"redis-backup.*\", namespace=\"novasight\"}) by (job_name)",
          "legendFormat": "Redis",
          "refId": "C"
        }
      ],
      "title": "Successful Backups Over Time",
      "type": "timeseries"
    },
    {
      "datasource": {
        "type": "prometheus",
        "uid": "${datasource}"
      },
      "fieldConfig": {
        "defaults": {
          "color": {
            "mode": "palette-classic"
          },
          "custom": {
            "axisCenteredZero": false,
            "axisColorMode": "text",
            "axisLabel": "",
            "axisPlacement": "auto",
            "barAlignment": 0,
            "drawStyle": "line",
            "fillOpacity": 10,
            "gradientMode": "none",
            "hideFrom": {
              "legend": false,
              "tooltip": false,
              "viz": false
            },
            "lineInterpolation": "linear",
            "lineWidth": 1,
            "pointSize": 5,
            "scaleDistribution": {
              "type": "linear"
            },
            "showPoints": "never",
            "spanNulls": false,
            "stacking": {
              "group": "A",
              "mode": "none"
            },
            "thresholdsStyle": {
              "mode": "line"
            }
          },
          "mappings": [],
          "thresholds": {
            "mode": "absolute",
            "steps": [
              {
                "color": "green",
                "value": null
              },
              {
                "color": "red",
                "value": 1
              }
            ]
          },
          "unit": "short"
        }
      },
      "gridPos": {
        "h": 8,
        "w": 12,
        "x": 12,
        "y": 10
      },
      "id": 7,
      "options": {
        "legend": {
          "calcs": [],
          "displayMode": "list",
          "placement": "bottom",
          "showLegend": true
        },
        "tooltip": {
          "mode": "multi",
          "sort": "desc"
        }
      },
      "targets": [
        {
          "expr": "sum(kube_job_status_failed{job_name=~\".*-backup.*\", namespace=\"novasight\"}) by (job_name)",
          "legendFormat": "{{job_name}}",
          "refId": "A"
        }
      ],
      "title": "Failed Backup Jobs",
      "type": "timeseries"
    },
    {
      "datasource": {
        "type": "prometheus",
        "uid": "${datasource}"
      },
      "fieldConfig": {
        "defaults": {
          "color": {
            "mode": "thresholds"
          },
          "custom": {
            "align": "auto",
            "cellOptions": {
              "type": "auto"
            },
            "inspect": false
          },
          "mappings": [],
          "thresholds": {
            "mode": "absolute",
            "steps": [
              {
                "color": "green",
                "value": null
              }
            ]
          }
        },
        "overrides": [
          {
            "matcher": {
              "id": "byName",
              "options": "Status"
            },
            "properties": [
              {
                "id": "custom.cellOptions",
                "value": {
                  "mode": "basic",
                  "type": "color-background"
                }
              },
              {
                "id": "mappings",
                "value": [
                  {
                    "options": {
                      "0": {
                        "color": "red",
                        "index": 1,
                        "text": "Failed"
                      },
                      "1": {
                        "color": "green",
                        "index": 0,
                        "text": "Succeeded"
                      }
                    },
                    "type": "value"
                  }
                ]
              }
            ]
          }
        ]
      },
      "gridPos": {
        "h": 8,
        "w": 24,
        "x": 0,
        "y": 18
      },
      "id": 8,
      "options": {
        "cellHeight": "sm",
        "footer": {
          "countRows": false,
          "fields": "",
          "reducer": ["sum"],
          "show": false
        },
        "showHeader": true
      },
      "targets": [
        {
          "expr": "kube_job_info{job_name=~\".*-backup.*\", namespace=\"novasight\"}",
          "format": "table",
          "instant": true,
          "refId": "A"
        }
      ],
      "title": "Recent Backup Jobs",
      "transformations": [
        {
          "id": "organize",
          "options": {
            "excludeByName": {
              "__name__": true,
              "container": true,
              "endpoint": true,
              "instance": true,
              "pod": true,
              "service": true
            },
            "indexByName": {},
            "renameByName": {
              "job_name": "Job Name",
              "namespace": "Namespace"
            }
          }
        }
      ],
      "type": "table"
    },
    {
      "datasource": {
        "type": "prometheus",
        "uid": "${datasource}"
      },
      "fieldConfig": {
        "defaults": {
          "color": {
            "mode": "palette-classic"
          },
          "custom": {
            "axisCenteredZero": false,
            "axisColorMode": "text",
            "axisLabel": "",
            "axisPlacement": "auto",
            "barAlignment": 0,
            "drawStyle": "line",
            "fillOpacity": 10,
            "gradientMode": "none",
            "hideFrom": {
              "legend": false,
              "tooltip": false,
              "viz": false
            },
            "lineInterpolation": "linear",
            "lineWidth": 1,
            "pointSize": 5,
            "scaleDistribution": {
              "type": "linear"
            },
            "showPoints": "never",
            "spanNulls": false,
            "stacking": {
              "group": "A",
              "mode": "none"
            },
            "thresholdsStyle": {
              "mode": "off"
            }
          },
          "mappings": [],
          "thresholds": {
            "mode": "absolute",
            "steps": [
              {
                "color": "green",
                "value": null
              }
            ]
          },
          "unit": "short"
        }
      },
      "gridPos": {
        "h": 8,
        "w": 12,
        "x": 0,
        "y": 26
      },
      "id": 9,
      "options": {
        "legend": {
          "calcs": [],
          "displayMode": "list",
          "placement": "bottom",
          "showLegend": true
        },
        "tooltip": {
          "mode": "single",
          "sort": "none"
        }
      },
      "targets": [
        {
          "expr": "pg_stat_archiver_archived_count{namespace=\"novasight\"}",
          "legendFormat": "Archived",
          "refId": "A"
        },
        {
          "expr": "pg_stat_archiver_failed_count{namespace=\"novasight\"}",
          "legendFormat": "Failed",
          "refId": "B"
        }
      ],
      "title": "PostgreSQL WAL Archiving",
      "type": "timeseries"
    },
    {
      "datasource": {
        "type": "prometheus",
        "uid": "${datasource}"
      },
      "fieldConfig": {
        "defaults": {
          "color": {
            "mode": "palette-classic"
          },
          "custom": {
            "hideFrom": {
              "legend": false,
              "tooltip": false,
              "viz": false
            }
          },
          "mappings": [],
          "unit": "bytes"
        }
      },
      "gridPos": {
        "h": 8,
        "w": 12,
        "x": 12,
        "y": 26
      },
      "id": 10,
      "options": {
        "legend": {
          "displayMode": "list",
          "placement": "right",
          "showLegend": true
        },
        "pieType": "pie",
        "reduceOptions": {
          "calcs": ["lastNotNull"],
          "fields": "",
          "values": false
        },
        "tooltip": {
          "mode": "single",
          "sort": "none"
        }
      },
      "targets": [
        {
          "expr": "aws_s3_bucket_size_bytes{bucket=\"novasight-backups\", prefix=\"postgresql\"}",
          "legendFormat": "PostgreSQL",
          "refId": "A"
        },
        {
          "expr": "aws_s3_bucket_size_bytes{bucket=\"novasight-backups\", prefix=\"clickhouse\"}",
          "legendFormat": "ClickHouse",
          "refId": "B"
        },
        {
          "expr": "aws_s3_bucket_size_bytes{bucket=\"novasight-backups\", prefix=\"redis\"}",
          "legendFormat": "Redis",
          "refId": "C"
        }
      ],
      "title": "Storage by Service",
      "type": "piechart"
    }
  ],
  "refresh": "1m",
  "schemaVersion": 38,
  "style": "dark",
  "tags": ["novasight", "backup", "operations"],
  "templating": {
    "list": [
      {
        "current": {
          "selected": false,
          "text": "Prometheus",
          "value": "prometheus"
        },
        "hide": 0,
        "includeAll": false,
        "label": "Data Source",
        "multi": false,
        "name": "datasource",
        "options": [],
        "query": "prometheus",
        "queryValue": "",
        "refresh": 1,
        "regex": "",
        "skipUrlSync": false,
        "type": "datasource"
      }
    ]
  },
  "time": {
    "from": "now-7d",
    "to": "now"
  },
  "timepicker": {},
  "timezone": "",
  "title": "NovaSight - Backup Dashboard",
  "uid": "novasight-backup",
  "version": 1,
  "weekStart": ""
}
